{
    "subjects": [
      {
        "name": "Mathematics",
        "chapters": [
          {
            "name": "Chapter 1: Numbers",
            "lessons": [
              {
                "title": "Introduction to Numbers",
                "type": "youtube",
                "url": "https://www.youtube.com/embed/AF31lWJJSgg"
              }
            ],
            "qa": {
                "type": "html",
                "path": "data/Mathematics/Chapter1/qa.html"
            }
          },
          {
            "name": "Fundamentals for Algebra",
            "lessons": [
              {
                "title": "Fundamentals for Algebra",
                "type": "youtube",
                "url": "https://www.youtube.com/embed/nHVfIxiGYfc"
              }
            ],
            "qa": {
                "type": "html",
                "path": "data/Mathematics/FundamentalsForAlgebra/qa.html"
            }
          }
        ]
      },
      {
        "name": "Biology",
        "chapters": [
          {
            "name": "Chapter 1: Leaf",
            "lessons": [
              {
                "title": "Leaf",
                "type": "youtube",
                "url": "https://www.youtube.com/embed/7hzbLqx_s2k"
              }
            ],
            "qa": {
                "type": "html",
                "path": "data/Biology/Chapter1/qa.html"
            }
          }
        ]
      }, 
      {
        "name": "History",
        "chapters": [
          {
            "name": "Egyptian History",
            "lessons": [
              {
                "title": "Egyptian History video",
                "type": "youtube",
                "url": "https://www.youtube.com/embed/8DOpD5Wa2Xc"
              }
            ]   ,
            "qa": {
              "type": "html",
              "path": "data/history/Egyptian/qa.html"
          }   
          },
          {
            "name": "The Mesopotamian Civilization",
            "lessons": [
              {
                "title": "Introduction to Mesopotamia",
                "type": "youtube",
                "url": "https://www.youtube.com/embed/7glMyuMY84w"
              }
            ],
            "qa": {
              "type": "html",
              "path": "data/History/MesopotamianCivilization/qa.html"
            }
          }
        ]
      },
      {
        "name": "Physics",
        "chapters": [
          {
            "name": "Chapter 1: Matter",
            "lessons": [
              {
                "title": "Matter",
                "type": "youtube",
                "url": "https://www.youtube.com/embed/WFOApNmVwm0?t=51"
              }
            ],
            "qa": {
              "type": "html",
              "path": "data/Physics/Matter/qa.html"
          }   
          }
        ]
      },
      {
        "name": "Chemistry",
        "chapters": [
          {
            "name": "Chapter 1: Introduction to chemistry",
            "lessons": [
              {
                "title": "Introduction to chemistry",
                "type": "youtube",
                "url": "https://www.youtube.com/embed/w_jhb7XOZkk?t=103"
              }
            ],
            "qa": {
              "type": "html",
              "path": "data/Chemistry/Chapter1/qa.html"
          }            
          }
        ]
      },
      {
        "name": "Geography",
        "chapters": [
          {
            "name": "Chapter Maps",
            "lessons": [
              {
                "title": "Introduction to Maps",
                "type": "youtube",
                "url": "https://www.youtube.com/embed/ZaM6IB-a7co"
              }
            ],
            "qa": {
              "type": "html",
              "path": "data/Geography/Chapter1/qa.html"
          }         
          }
        ]
      },
      {
        "name": "Computers",
        "chapters": [
          {
            "name": "Introduction to Languages",
            "lessons": [
              {
                "title": "Programming Languages Basics",
                "type": "youtube",
                "url": "https://www.youtube.com/embed/oNv7sqR5ozg"
              }
            ],
            "qa_pdf": "data/Computers/Chapter1/qa.pdf"
          }
        ]
      },
      {
        "name": "Hindi",
        "chapters": [
          {
            "name": "Chapter 1: Introduction",
            "lessons": [
              {
                "title": "Dhan Ki khoz",
                "type": "youtube",
                "url": "https://www.youtube.com/embed/An7CEzAG8fM"
              }
            ],
            "qa": {
              "type": "html",
              "path": "data/Hindi/DhanKikhoz/qa.html"
          }
          }
        ]
      }
    ]
  }